LICENSE
README.md
setup.py
qiskit_xyz2pdb.egg-info/PKG-INFO
qiskit_xyz2pdb.egg-info/SOURCES.txt
qiskit_xyz2pdb.egg-info/dependency_links.txt
qiskit_xyz2pdb.egg-info/entry_points.txt
qiskit_xyz2pdb.egg-info/not-zip-safe
qiskit_xyz2pdb.egg-info/top_level.txt
xyz2pdb/__init__.py
xyz2pdb/xyz2pdb.py