Metadata-Version: 2.1
Name: qiskit-xyz2pdb
Version: 0.1.0
Summary: A simple Python package to convert XYZ files from Qiskit output into PDB structures
Home-page: http://github.com/thepineapplepirate/qiskit-xyz2pdb
Download-URL: https://pypi.org/project/qiskit-xyz2pdb/
Author: Bryan Raubenolt
Author-email: raubenb@ccf.org
License: MIT
Project-URL: Issues, https://github.com/thepineapplepirate/qiskit-xyz2pdb/issues
Project-URL: Source, https://github.com/thepineapplepirate/qiskit-xyz2pdb
Keywords: bioinformatics,chemistry,pdb,proteins,qiskit,quantum
Classifier: Environment :: Console
Classifier: Intended Audience :: Science/Research
Classifier: License :: OSI Approved :: MIT License
Classifier: Natural Language :: English
Classifier: Programming Language :: Python :: 3
Classifier: Topic :: Scientific/Engineering :: Bio-Informatics
Requires-Python: >=3.6
License-File: LICENSE
